{
    "id": "GameplayEnhancements",
    "Title": "Gameplay Enhancements",
    "Author": "Dante",
    "Description": "1. Fixes the camp recruit button disappearing after save/load.\n2. Optionally caches the Encyclopedia UI and defers tab loading to eliminate freezes.\n3. Configurable starting Mana, Gold, and Soulstones for new runs.\n4. Mod compatibility fixes for broken skill tooltips and outdated buffs.",
    "Version": "1.0.0",
    "Cover": "",
    "ModSettingEntries": [
        {
            "SettingType": "DropdownSetting",
            "SettingKey": "CollectionsOptimization",
            "DisplayName": "Cache Encyclopedia",
            "Description": "Caches the Encyclopedia UI and defers tab loading to eliminate freezes. Experimental — disable if the Encyclopedia behaves oddly.",
            "InitValue": 0,
            "Options": ["Off", "On"]
        },
        {
            "SettingType": "SliderSetting",
            "SettingKey": "StartingMana",
            "DisplayName": "Starting Mana",
            "Description": "Mana (AP) at the start of a new run.",
            "InitValue": 3,
            "Min": 1,
            "Max": 10,
            "StepSize": 1
        },
        {
            "SettingType": "SliderSetting",
            "SettingKey": "StartingGold",
            "DisplayName": "Starting Gold",
            "Description": "Gold at the start of a new run.",
            "InitValue": 0,
            "Min": 0,
            "Max": 1000,
            "StepSize": 50
        },
        {
            "SettingType": "SliderSetting",
            "SettingKey": "StartingSoulstones",
            "DisplayName": "Starting Soulstones",
            "Description": "Soulstones at the start of a new run.",
            "InitValue": 0,
            "Min": 0,
            "Max": 25,
            "StepSize": 1
        }
    ],
    "DefaultAssetBundlePath": "",
    "Dependencies": [],
    "NeedRestartWhenSettingChanged": false,
    "NeedReloadAllWhenEnabled": false,
    "NeedRestartWhenEnabled": true,
    "Uploader": "Dante",
    "TagList": ["QoL"],
    "Visibility": "Public",
    "OnlyUploadFiles": true
}
